nixhelloworld/__init__.py
nixhelloworld/helloworld.py
nixhelloworld-0.0.1.dist-info/LICENSE.txt
nixhelloworld-0.0.1.dist-info/METADATA
nixhelloworld-0.0.1.dist-info/WHEEL
nixhelloworld-0.0.1.dist-info/top_level.txt
nixhelloworld-0.0.1.dist-info/RECORD
