Metadata-Version: 2.1
Name: nixhelloworld
Version: 0.0.1
Summary: Simple hello world script
Author: Nick Fleming
License-File: LICENSE.txt
